big_positive_int_field/__init__.py
big_positive_int_field/fields.py
django_big_positive_int_field-1.1.0.dist-info/AUTHORS
django_big_positive_int_field-1.1.0.dist-info/LICENSE
django_big_positive_int_field-1.1.0.dist-info/METADATA
django_big_positive_int_field-1.1.0.dist-info/WHEEL
django_big_positive_int_field-1.1.0.dist-info/top_level.txt
django_big_positive_int_field-1.1.0.dist-info/RECORD
