Metadata-Version: 2.1
Name: django-big-positive-int-field
Version: 1.1.0
Summary: Generic model field for storing big integer field.
Home-page: https://github.com/meetrks/django-big-positive-int-field
Author: Rahul
Author-email: skrsinghrahul@gmail.com
License: UNKNOWN
Platform: UNKNOWN
Classifier: Development Status :: 3 - Alpha
Classifier: Intended Audience :: Developers
Classifier: License :: OSI Approved :: MIT License
Classifier: Operating System :: OS Independent
Classifier: Programming Language :: Python
Classifier: Topic :: Software Development :: Libraries :: Python Modules
Requires-Dist: django (>=2.2)
